{"爬虫作者": "曾影穹(vcrting@163.com)", "author": "上傳作者：月工月工女子", "cover": "http://www.fk5378.com/upload/u9/DoZ/7bc81857edae42b989c9eda1f515d6f7.jpg", "item_url": "http://www.fk5378.com/video/1288", "publish_date": "上傳日期：2018-12-08", "see_num": "瀏覽次數：226,000", "tags": ["做愛", "大學生", "娛樂", "嫩模", "學生", "學生妹", "學生妹系列", "打砲", "本土", "無套", "男友視角", "精品資源網曝門事件"], "time_num": "影片長度：00:08:12", "title": "湖南美女模特张茹出名前与男友啪啪自拍流出SM", "vedio_url": "http://video2.fkvideo.cc/5bb684a265c043c0b5df91a05eb8ab50.mp4", "pipeline_use_num": 129, "spider_start_time": "2019-03-01 18:34:24", "spider_use_time": "2019-03-01 18:34:24"}